Metadata-Version: 1.0
Name: distributions-cf
Version: 0.1
Summary: Gaussian distributions
Home-page: UNKNOWN
Author: CF Khor
Author-email: khorcf@gmail.com
License: UNKNOWN
Platform: UNKNOWN
